types_wtforms-3.2.1.20250602.dist-info/licenses/LICENSE
wtforms-stubs/METADATA.toml
wtforms-stubs/__init__.pyi
wtforms-stubs/form.pyi
wtforms-stubs/i18n.pyi
wtforms-stubs/meta.pyi
wtforms-stubs/py.typed
wtforms-stubs/utils.pyi
wtforms-stubs/validators.pyi
wtforms-stubs/csrf/__init__.pyi
wtforms-stubs/csrf/core.pyi
wtforms-stubs/csrf/session.pyi
wtforms-stubs/fields/__init__.pyi
wtforms-stubs/fields/choices.pyi
wtforms-stubs/fields/core.pyi
wtforms-stubs/fields/datetime.pyi
wtforms-stubs/fields/form.pyi
wtforms-stubs/fields/list.pyi
wtforms-stubs/fields/numeric.pyi
wtforms-stubs/fields/simple.pyi
wtforms-stubs/widgets/__init__.pyi
wtforms-stubs/widgets/core.pyi
types_wtforms-3.2.1.20250602.dist-info/METADATA
types_wtforms-3.2.1.20250602.dist-info/WHEEL
types_wtforms-3.2.1.20250602.dist-info/top_level.txt
types_wtforms-3.2.1.20250602.dist-info/RECORD
